{"v":"5.9.0","fr":120,"ip":0,"op":373,"w":3024,"h":1964,"nm":"1","ddd":0,"assets":[{"id":"comp_0","nm":"quantum","fr":120,"layers":[{"ddd":0,"ind":1,"ty":4,"nm":"Camada de forma 4","sr":1,"ks":{"o":{"a":0,"k":100,"ix":11},"r":{"a":0,"k":0,"ix":10},"p":{"a":0,"k":[756,491,0],"ix":2,"l":2},"a":{"a":0,"k":[0,0,0],"ix":1,"l":2},"s":{"a":0,"k":[100,100,100],"ix":6,"l":2}},"ao":0,"shapes":[{"ty":"gr","it":[{"ind":0,"ty":"sh","ix":1,"ks":{"a":0,"k":{"i":[[0,0],[0,0],[0,0],[0,0],[0,0],[0,0]],"o":[[0,0],[0,0],[0,0],[0,0],[0,0],[0,0]],"v":[[28.42,-32.84],[-94.1,-154.22],[-214.34,-154.22],[97.25,154.22],[214.34,154.22],[50.13,-10]],"c":true},"ix":2},"nm":"Caminho 1","mn":"ADBE Vector Shape - Group","hd":false},{"ty":"st","c":{"a":0,"k":[0.815685975318,0.815685975318,0.815685975318,1],"ix":3},"o":{"a":0,"k":9,"ix":4},"w":{"a":0,"k":0,"ix":5},"lc":1,"lj":1,"ml":4,"bm":0,"nm":"Traçado 1","mn":"ADBE Vector Graphic - Stroke","hd":false},{"ty":"fl","c":{"a":0,"k":[0,0,0,1],"ix":4},"o":{"a":0,"k":100,"ix":5},"r":1,"bm":0,"nm":"Preenchimento 1","mn":"ADBE Vector Graphic - Fill","hd":false},{"ty":"tr","p":{"a":0,"k":[-433.5,-209],"ix":2},"a":{"a":0,"k":[0,0],"ix":1},"s":{"a":0,"k":[28,28],"ix":3},"r":{"a":0,"k":0,"ix":6},"o":{"a":0,"k":100,"ix":7},"sk":{"a":0,"k":0,"ix":4},"sa":{"a":0,"k":0,"ix":5},"nm":"Transformar"}],"nm":"Forma 2","np":3,"cix":2,"bm":0,"ix":1,"mn":"ADBE Vector Group","hd":false},{"ty":"gr","it":[{"ind":0,"ty":"sh","ix":1,"ks":{"a":0,"k":{"i":[[221.91,0],[0,-222.2],[-224.2,0],[-58.83,32.56],[0,0],[37.42,0],[0,176.78],[-181.93,0],[0,-170.78],[45.41,-53.98],[0,0],[0,98.53]],"o":[[-222.2,0],[0,222.2],[63.12,0],[0,0],[-40.55,18.56],[-167.64,0],[0,-176.78],[181.93,0],[0,64.26],[0,0],[62.26,-70.26],[0.58,-222.19]],"v":[[0,-404.12],[-406.12,0],[0,404.12],[191.63,353.28],[122.8,285.31],[-0.01,313.87],[-309.31,0.29],[0,-313.59],[309.3,-0.01],[240.47,193.91],[307.01,261.88],[405.54,-0.01]],"c":true},"ix":2},"nm":"Caminho 1","mn":"ADBE Vector Shape - Group","hd":false},{"ty":"st","c":{"a":0,"k":[0.815685975318,0.815685975318,0.815685975318,1],"ix":3},"o":{"a":0,"k":0,"ix":4},"w":{"a":0,"k":0,"ix":5},"lc":1,"lj":1,"ml":4,"bm":0,"nm":"Traçado 1","mn":"ADBE Vector Graphic - Stroke","hd":false},{"ty":"fl","c":{"a":0,"k":[0.007843137255,0.007843137255,0.007843137255,1],"ix":4},"o":{"a":0,"k":100,"ix":5},"r":1,"bm":0,"nm":"Preenchimento 1","mn":"ADBE Vector Graphic - Fill","hd":false},{"ty":"tr","p":{"a":0,"k":[-487,-278],"ix":2},"a":{"a":0,"k":[0,0],"ix":1},"s":{"a":0,"k":[28,28],"ix":3},"r":{"a":0,"k":0,"ix":6},"o":{"a":0,"k":100,"ix":7},"sk":{"a":0,"k":0,"ix":4},"sa":{"a":0,"k":0,"ix":5},"nm":"Transformar"}],"nm":"Forma 1","np":3,"cix":2,"bm":0,"ix":2,"mn":"ADBE Vector Group","hd":false}],"ip":377,"op":1260,"st":38,"bm":0},{"ddd":0,"ind":2,"ty":4,"nm":"Camada de forma 3","sr":1,"ks":{"o":{"a":0,"k":100,"ix":11},"r":{"a":0,"k":0,"ix":10},"p":{"a":0,"k":[715,1122,0],"ix":2,"l":2},"a":{"a":0,"k":[0,0,0],"ix":1,"l":2},"s":{"a":0,"k":[100,100,100],"ix":6,"l":2}},"ao":0,"hasMask":true,"masksProperties":[{"inv":true,"mode":"a","pt":{"a":0,"k":{"i":[[0,0],[0,0],[0,0],[0,0]],"o":[[0,0],[0,0],[0,0],[0,0]],"v":[[685,-791],[-363,-791],[-363,-537],[685,-537]],"c":true},"ix":1},"o":{"a":0,"k":100,"ix":3},"x":{"a":0,"k":0,"ix":4},"nm":"Máscara 1"}],"shapes":[{"ty":"gr","it":[{"ind":0,"ty":"sh","ix":1,"ks":{"a":0,"k":{"i":[[0,0],[12.79,0],[0,43.52],[0,0],[0,0],[0,0],[-14.96,-14.34],[-21.56,0],[-14.55,12.07],[0,26.72],[0,0],[0,0],[0,0],[0,0]],"o":[[0,43.63],[-12.79,0],[0,0],[0,0],[0,0],[0,26.72],[14.65,12.07],[21.56,0],[14.96,-14.34],[0,0],[0,0],[0,0],[0,0],[0,0]],"v":[[44.66,38.425],[0.1,88.345],[-44.46,38.425],[-44.46,-119.915],[-78.81,-119.915],[-78.81,39.455],[-54.98,99.905],[0,119.915],[54.98,99.905],[78.81,39.455],[78.81,-119.915],[44.46,-119.915],[44.46,38.525],[44.67,38.425]],"c":true},"ix":2},"nm":"Caminho 1","mn":"ADBE Vector Shape - Group","hd":false},{"ty":"st","c":{"a":0,"k":[0.905882352941,0.905882352941,0.905882352941,1],"ix":3},"o":{"a":0,"k":100,"ix":4},"w":{"a":0,"k":0,"ix":5},"lc":1,"lj":1,"ml":4,"bm":0,"nm":"Traçado 1","mn":"ADBE Vector Graphic - Stroke","hd":false},{"ty":"fl","c":{"a":0,"k":[0,0,0,1],"ix":4},"o":{"a":0,"k":100,"ix":5},"r":1,"bm":0,"nm":"Preenchimento 1","mn":"ADBE Vector Graphic - Fill","hd":false},{"ty":"tr","p":{"a":1,"k":[{"i":{"x":0.667,"y":1},"o":{"x":0.333,"y":0},"t":379,"s":[-250,-692.5],"to":[0,0],"ti":[0,0]},{"t":382,"s":[-250,-895.5]}],"ix":2},"a":{"a":0,"k":[0,0],"ix":1},"s":{"a":0,"k":[75.625,76.59],"ix":3},"r":{"a":0,"k":0,"ix":6},"o":{"a":0,"k":100,"ix":7},"sk":{"a":0,"k":0,"ix":4},"sa":{"a":0,"k":0,"ix":5},"nm":"Transformar"}],"nm":"Forma 6","np":3,"cix":2,"bm":0,"ix":1,"mn":"ADBE Vector Group","hd":false},{"ty":"gr","it":[{"ind":0,"ty":"sh","ix":1,"ks":{"a":0,"k":{"i":[[0,0],[0,0],[0,0],[0,0],[0,0],[0,0],[0,0],[0,0],[0,0],[0,0],[0,0],[0,0]],"o":[[0,0],[0,0],[0,0],[0,0],[0,0],[0,0],[0,0],[0,0],[0,0],[0,0],[0,0],[0,0]],"v":[[-15.42,-117.695],[-104.85,117.695],[-68.54,117.695],[-42.45,48.275],[-30.38,16.815],[-0.15,-73.235],[0.46,-73.235],[30.38,16.815],[42.14,48.275],[68.23,117.695],[104.85,117.695],[15.42,-117.695]],"c":true},"ix":2},"nm":"Caminho 1","mn":"ADBE Vector Shape - Group","hd":false},{"ty":"st","c":{"a":0,"k":[0.905882352941,0.905882352941,0.905882352941,1],"ix":3},"o":{"a":0,"k":100,"ix":4},"w":{"a":0,"k":0,"ix":5},"lc":1,"lj":1,"ml":4,"bm":0,"nm":"Traçado 1","mn":"ADBE Vector Graphic - Stroke","hd":false},{"ty":"fl","c":{"a":0,"k":[0,0,0,1],"ix":4},"o":{"a":0,"k":100,"ix":5},"r":1,"bm":0,"nm":"Preenchimento 1","mn":"ADBE Vector Graphic - Fill","hd":false},{"ty":"tr","p":{"a":1,"k":[{"i":{"x":0.667,"y":1},"o":{"x":0.333,"y":0},"t":379,"s":[-97.5,-691.5],"to":[0,0],"ti":[0,0]},{"t":385,"s":[-97.5,-894.5]}],"ix":2},"a":{"a":0,"k":[0,0],"ix":1},"s":{"a":0,"k":[75.6,77.278],"ix":3},"r":{"a":0,"k":0,"ix":6},"o":{"a":0,"k":100,"ix":7},"sk":{"a":0,"k":0,"ix":4},"sa":{"a":0,"k":0,"ix":5},"nm":"Transformar"}],"nm":"Forma 1","np":3,"cix":2,"bm":0,"ix":2,"mn":"ADBE Vector Group","hd":false},{"ty":"gr","it":[{"ind":0,"ty":"sh","ix":1,"ks":{"a":0,"k":{"i":[[0,0],[0,0],[0,0],[0,0],[0,0],[0,0],[0,0],[0,0],[0,0],[0,0],[0,0],[0,0]],"o":[[0,0],[0,0],[0,0],[0,0],[0,0],[0,0],[0,0],[0,0],[0,0],[0,0],[0,0],[0,0]],"v":[[59.155,61.375],[58.535,61.375],[-56.065,-117.695],[-93.505,-117.695],[-93.505,117.695],[-59.155,117.695],[-59.155,-64.255],[-58.545,-64.255],[57.815,117.695],[93.505,117.695],[93.505,-117.695],[59.155,-117.695]],"c":true},"ix":2},"nm":"Caminho 1","mn":"ADBE Vector Shape - Group","hd":false},{"ty":"st","c":{"a":0,"k":[0.905882352941,0.905882352941,0.905882352941,1],"ix":3},"o":{"a":0,"k":100,"ix":4},"w":{"a":0,"k":0,"ix":5},"lc":1,"lj":1,"ml":4,"bm":0,"nm":"Traçado 1","mn":"ADBE Vector Graphic - Stroke","hd":false},{"ty":"fl","c":{"a":0,"k":[0,0,0,1],"ix":4},"o":{"a":0,"k":100,"ix":5},"r":1,"bm":0,"nm":"Preenchimento 1","mn":"ADBE Vector Graphic - Fill","hd":false},{"ty":"tr","p":{"a":1,"k":[{"i":{"x":0.667,"y":1},"o":{"x":0.333,"y":0},"t":379,"s":[75.5,-691.5],"to":[0,0],"ti":[0,0]},{"t":388,"s":[75.5,-894.5]}],"ix":2},"a":{"a":0,"k":[0,0],"ix":1},"s":{"a":0,"k":[75.6,76.874],"ix":3},"r":{"a":0,"k":0,"ix":6},"o":{"a":0,"k":100,"ix":7},"sk":{"a":0,"k":0,"ix":4},"sa":{"a":0,"k":0,"ix":5},"nm":"Transformar"}],"nm":"Forma 2","np":3,"cix":2,"bm":0,"ix":3,"mn":"ADBE Vector Group","hd":false},{"ty":"gr","it":[{"ind":0,"ty":"sh","ix":1,"ks":{"a":0,"k":{"i":[[0,0],[0,0],[0,0],[0,0],[0,0],[0,0],[0,0],[0,0],[0,0],[0,0],[0,0],[0,0]],"o":[[0,0],[0,0],[0,0],[0,0],[0,0],[0,0],[0,0],[0,0],[0,0],[0,0],[0,0],[0,0]],"v":[[-62.35,-117.695],[-69.99,-117.695],[-69.99,-86.235],[-62.35,-86.235],[-17.18,-86.235],[-17.18,117.695],[17.17,117.695],[17.17,-86.235],[62.35,-86.235],[69.99,-86.235],[69.99,-117.695],[62.35,-117.695]],"c":true},"ix":2},"nm":"Caminho 1","mn":"ADBE Vector Shape - Group","hd":false},{"ty":"st","c":{"a":0,"k":[0.905882352941,0.905882352941,0.905882352941,1],"ix":3},"o":{"a":0,"k":100,"ix":4},"w":{"a":0,"k":0,"ix":5},"lc":1,"lj":1,"ml":4,"bm":0,"nm":"Traçado 1","mn":"ADBE Vector Graphic - Stroke","hd":false},{"ty":"fl","c":{"a":0,"k":[0,0,0,1],"ix":4},"o":{"a":0,"k":100,"ix":5},"r":1,"bm":0,"nm":"Preenchimento 1","mn":"ADBE Vector Graphic - Fill","hd":false},{"ty":"tr","p":{"a":1,"k":[{"i":{"x":0.667,"y":1},"o":{"x":0.333,"y":0},"t":379,"s":[220,-691.5],"to":[0,0],"ti":[0,0]},{"t":391,"s":[220,-894.5]}],"ix":2},"a":{"a":0,"k":[0,0],"ix":1},"s":{"a":0,"k":[76.665,77.302],"ix":3},"r":{"a":0,"k":0,"ix":6},"o":{"a":0,"k":100,"ix":7},"sk":{"a":0,"k":0,"ix":4},"sa":{"a":0,"k":0,"ix":5},"nm":"Transformar"}],"nm":"Forma 3","np":3,"cix":2,"bm":0,"ix":4,"mn":"ADBE Vector Group","hd":false},{"ty":"gr","it":[{"ind":0,"ty":"sh","ix":1,"ks":{"a":0,"k":{"i":[[0,0],[12.79,0],[0,43.52],[0,0],[0,0],[0,0],[-14.96,-14.34],[-21.56,0],[-14.55,12.07],[0,26.72],[0,0],[0,0],[0,0],[0,0]],"o":[[0,43.63],[-12.79,0],[0,0],[0,0],[0,0],[0,26.72],[14.65,12.07],[21.56,0],[14.96,-14.34],[0,0],[0,0],[0,0],[0,0],[0,0]],"v":[[44.66,38.425],[0.1,88.345],[-44.46,38.425],[-44.46,-119.915],[-78.81,-119.915],[-78.81,39.455],[-54.98,99.905],[0,119.915],[54.98,99.905],[78.81,39.455],[78.81,-119.915],[44.46,-119.915],[44.46,38.525],[44.67,38.425]],"c":true},"ix":2},"nm":"Caminho 1","mn":"ADBE Vector Shape - Group","hd":false},{"ty":"st","c":{"a":0,"k":[0.905882352941,0.905882352941,0.905882352941,1],"ix":3},"o":{"a":0,"k":100,"ix":4},"w":{"a":0,"k":0,"ix":5},"lc":1,"lj":1,"ml":4,"bm":0,"nm":"Traçado 1","mn":"ADBE Vector Graphic - Stroke","hd":false},{"ty":"fl","c":{"a":0,"k":[0,0,0,1],"ix":4},"o":{"a":0,"k":100,"ix":5},"r":1,"bm":0,"nm":"Preenchimento 1","mn":"ADBE Vector Graphic - Fill","hd":false},{"ty":"tr","p":{"a":1,"k":[{"i":{"x":0.667,"y":1},"o":{"x":0.333,"y":0},"t":379,"s":[353,-692.5],"to":[0,0],"ti":[0,0]},{"t":394,"s":[353,-895.5]}],"ix":2},"a":{"a":0,"k":[0,0],"ix":1},"s":{"a":0,"k":[76.541,76.857],"ix":3},"r":{"a":0,"k":0,"ix":6},"o":{"a":0,"k":100,"ix":7},"sk":{"a":0,"k":0,"ix":4},"sa":{"a":0,"k":0,"ix":5},"nm":"Transformar"}],"nm":"Forma 4","np":3,"cix":2,"bm":0,"ix":5,"mn":"ADBE Vector Group","hd":false},{"ty":"gr","it":[{"ind":0,"ty":"sh","ix":1,"ks":{"a":0,"k":{"i":[[0,0],[0,0],[0,0],[0,0],[0,0],[0,0],[0,0],[0,0],[0,0],[0,0],[0,0],[0,0],[0,0],[0,0],[0,0]],"o":[[0,0],[0,0],[0,0],[0,0],[0,0],[0,0],[0,0],[0,0],[0,0],[0,0],[0,0],[0,0],[0,0],[0,0],[0,0]],"v":[[70.815,-117.695],[-0.155,62.615],[-70.815,-117.695],[-124.865,-117.695],[-124.865,117.695],[-90.515,117.695],[-90.515,-81.175],[-89.895,-81.175],[-10.365,117.695],[10.365,117.695],[89.585,-81.175],[90.515,-81.175],[90.515,117.695],[124.865,117.695],[124.865,-117.695]],"c":true},"ix":2},"nm":"Caminho 1","mn":"ADBE Vector Shape - Group","hd":false},{"ty":"st","c":{"a":0,"k":[0.905882352941,0.905882352941,0.905882352941,1],"ix":3},"o":{"a":0,"k":100,"ix":4},"w":{"a":0,"k":0,"ix":5},"lc":1,"lj":1,"ml":4,"bm":0,"nm":"Traçado 1","mn":"ADBE Vector Graphic - Stroke","hd":false},{"ty":"fl","c":{"a":0,"k":[0,0,0,1],"ix":4},"o":{"a":0,"k":100,"ix":5},"r":1,"bm":0,"nm":"Preenchimento 1","mn":"ADBE Vector Graphic - Fill","hd":false},{"ty":"tr","p":{"a":1,"k":[{"i":{"x":0.667,"y":1},"o":{"x":0.333,"y":0},"t":379,"s":[544.5,-692.5],"to":[0,0],"ti":[0,0]},{"t":397,"s":[544.5,-895.5]}],"ix":2},"a":{"a":0,"k":[0,0],"ix":1},"s":{"a":0,"k":[76.202,76.662],"ix":3},"r":{"a":0,"k":0,"ix":6},"o":{"a":0,"k":100,"ix":7},"sk":{"a":0,"k":0,"ix":4},"sa":{"a":0,"k":0,"ix":5},"nm":"Transformar"}],"nm":"Forma 5","np":3,"cix":2,"bm":0,"ix":6,"mn":"ADBE Vector Group","hd":false}],"ip":377,"op":1263,"st":142,"bm":0}]},{"id":"comp_1","nm":"Q","fr":120,"layers":[{"ddd":0,"ind":1,"ty":4,"nm":"Calque de forme 1","sr":1,"ks":{"o":{"a":1,"k":[{"i":{"x":[0.833],"y":[0.833]},"o":{"x":[0.167],"y":[0.167]},"t":367,"s":[100]},{"t":377,"s":[0]}],"ix":11},"r":{"a":1,"k":[{"i":{"x":[0.024],"y":[0.96]},"o":{"x":[0.964],"y":[0.009]},"t":58,"s":[0]},{"i":{"x":[0.667],"y":[1]},"o":{"x":[0.545],"y":[1.333]},"t":94,"s":[90]},{"i":{"x":[0.667],"y":[1]},"o":{"x":[0.333],"y":[0]},"t":201,"s":[90]},{"i":{"x":[0.833],"y":[1]},"o":{"x":[0.333],"y":[0]},"t":300,"s":[450]},{"t":359,"s":[450]}],"ix":10},"p":{"a":0,"k":[756,491,0],"ix":2,"l":2},"a":{"a":0,"k":[0,0,0],"ix":1,"l":2},"s":{"a":1,"k":[{"i":{"x":[0.374,0.374,0.667],"y":[0.073,0.073,1]},"o":{"x":[0.333,0.333,0.333],"y":[0,0,0]},"t":0,"s":[50,50,100]},{"t":58,"s":[59,59,100]}],"ix":6,"l":2}},"ao":0,"ef":[{"ty":5,"nm":"CC Light Sweep","np":11,"mn":"CC Light Sweep","ix":1,"en":1,"ef":[{"ty":3,"nm":"Center","mn":"CC Light Sweep-0001","ix":1,"v":{"a":1,"k":[{"i":{"x":0.833,"y":0.833},"o":{"x":0.167,"y":0.167},"t":0,"s":[521.121,257.374],"to":[0,0],"ti":[0,0]},{"i":{"x":0.833,"y":0.833},"o":{"x":0.167,"y":0.167},"t":138,"s":[993.121,730.374],"to":[0,0],"ti":[0,0]},{"i":{"x":0.833,"y":0.833},"o":{"x":0.167,"y":0.167},"t":301,"s":[749.121,246.374],"to":[0,0],"ti":[0,0]},{"t":304,"s":[619.121,252.374]}],"ix":1}},{"ty":0,"nm":"Direction","mn":"CC Light Sweep-0002","ix":2,"v":{"a":1,"k":[{"i":{"x":[0.833],"y":[0.833]},"o":{"x":[0.167],"y":[0.167]},"t":0,"s":[715.102]},{"i":{"x":[0.833],"y":[0.833]},"o":{"x":[0.167],"y":[0.167]},"t":302,"s":[1075.102]},{"t":304,"s":[1435.102]}],"ix":2}},{"ty":7,"nm":"Shape","mn":"CC Light Sweep-0003","ix":3,"v":{"a":0,"k":1,"ix":3}},{"ty":0,"nm":"Width","mn":"CC Light Sweep-0004","ix":4,"v":{"a":0,"k":200,"ix":4}},{"ty":0,"nm":"Sweep Intensity","mn":"CC Light Sweep-0005","ix":5,"v":{"a":0,"k":40,"ix":5}},{"ty":0,"nm":"Edge Intensity","mn":"CC Light Sweep-0006","ix":6,"v":{"a":0,"k":0,"ix":6}},{"ty":0,"nm":"Edge Thickness","mn":"CC Light Sweep-0007","ix":7,"v":{"a":0,"k":0,"ix":7}},{"ty":2,"nm":"Light Color","mn":"CC Light Sweep-0008","ix":8,"v":{"a":0,"k":[1,1,1,1],"ix":8}},{"ty":7,"nm":"Light Reception","mn":"CC Light Sweep-0009","ix":9,"v":{"a":0,"k":1,"ix":9}}]}],"shapes":[{"ty":"gr","it":[{"ind":0,"ty":"sh","ix":1,"ks":{"a":0,"k":{"i":[[0,0],[49.37,-21.22],[36.87,-37.19],[20.25,-47.88],[0,-53.93],[-21,-49.64],[-36.92,-37.17],[-47.71,-20.46],[-53.94,0],[-49.42,21.04],[-36.91,37.04],[-20.28,48],[0,54.39],[30.96,57.29],[0,0],[0,-38.21],[16.16,-38.22],[28.71,-28.74],[87.13,0],[58.09,56.25],[15.61,37.52],[0,44.64],[-16.73,39.09],[-29.4,28.13],[-37.91,14.99],[-42.5,0],[-50.9,-41.9],[0,0],[43.31,16.44],[48.29,0]],"o":[[-53.75,0],[-47.58,20.45],[-36.82,37.14],[-20.96,49.56],[0,53.93],[20.3,47.95],[36.96,37.21],[49.48,21.22],[53.94,0],[47.76,-20.33],[36.95,-37.07],[21.01,-49.74],[0,-61.74],[0,0],[17.82,39.56],[0,41.51],[-15.73,37.19],[-59.65,59.72],[-87.13,0],[-28.91,-28],[-16.19,-38.91],[0,-44.64],[15.99,-37.38],[28.91,-27.66],[38.52,-15.22],[68.89,0],[0,0],[-34.46,-30.06],[-44.96,-17.07],[0,0]],"v":[[-1.03,-403.005],[-156.44,-371.025],[-283.71,-284.155],[-369.71,-156.025],[-401.29,-0.285],[-369.63,155.795],[-283.39,284.085],[-155.78,371.005],[-0.02,402.985],[155.75,371.285],[283.35,284.835],[369.59,156.635],[401.26,-0.295],[352.6,-187.225],[288.68,-122.495],[316.69,-0.295],[292.33,119.865],[225.36,219.225],[0.27,311.835],[-224.93,224.605],[-292.03,125.865],[-316.43,-0.305],[-291.22,-126.495],[-222.81,-225.225],[-122.1,-289.495],[-0.01,-312.435],[193.76,-244.585],[257.72,-307.205],[140.54,-377.275],[0,-403.005]],"c":true},"ix":2},"nm":"Tracé 1","mn":"ADBE Vector Shape - Group","hd":false},{"ty":"st","c":{"a":1,"k":[{"i":{"x":[0.833],"y":[0.833]},"o":{"x":[0.167],"y":[0.167]},"t":327,"s":[0.823516845703,0.789520263672,0.745086669922,1]},{"t":328,"s":[1,1,1,1]}],"ix":3},"o":{"a":1,"k":[{"i":{"x":[0.833],"y":[0.833]},"o":{"x":[0.167],"y":[0.167]},"t":312,"s":[100]},{"t":320,"s":[0]}],"ix":4},"w":{"a":0,"k":4,"ix":5},"lc":2,"lj":2,"bm":0,"nm":"Contour 1","mn":"ADBE Vector Graphic - Stroke","hd":false},{"ty":"fl","c":{"a":1,"k":[{"i":{"x":[0.833],"y":[0.833]},"o":{"x":[0.167],"y":[0.167]},"t":552,"s":[1,1,1,1]},{"t":553,"s":[0,0,0,1]}],"ix":4},"o":{"a":1,"k":[{"i":{"x":[0.833],"y":[0.833]},"o":{"x":[0.167],"y":[0.167]},"t":309,"s":[0]},{"i":{"x":[0.833],"y":[0.833]},"o":{"x":[0.167],"y":[0.167]},"t":310,"s":[100]},{"i":{"x":[0.833],"y":[0.833]},"o":{"x":[0.167],"y":[0.167]},"t":367,"s":[100]},{"t":377,"s":[0]}],"ix":5},"r":1,"bm":0,"nm":"Fond 1","mn":"ADBE Vector Graphic - Fill","hd":false},{"ty":"tr","p":{"a":0,"k":[0,0],"ix":2},"a":{"a":0,"k":[0,0],"ix":1},"s":{"a":1,"k":[{"i":{"x":[0.833,0.833],"y":[1,1]},"o":{"x":[0.56,0.56],"y":[-0.175,-0.175]},"t":359,"s":[100,100]},{"i":{"x":[0.689,0.689],"y":[0.768,0.768]},"o":{"x":[0.559,0.559],"y":[0.014,0.014]},"t":367,"s":[80,80]},{"t":377,"s":[400,400]}],"ix":3},"r":{"a":0,"k":720,"ix":6},"o":{"a":1,"k":[{"i":{"x":[0.833],"y":[0.833]},"o":{"x":[0.167],"y":[0.167]},"t":367,"s":[100]},{"t":377,"s":[0]}],"ix":7},"sk":{"a":0,"k":0,"ix":4},"sa":{"a":0,"k":0,"ix":5},"nm":"Transformar"}],"nm":"Forme 1","np":3,"cix":2,"bm":0,"ix":1,"mn":"ADBE Vector Group","hd":false},{"ty":"tm","s":{"a":0,"k":0,"ix":1},"e":{"a":1,"k":[{"i":{"x":[0.833],"y":[0.833]},"o":{"x":[0.167],"y":[0.167]},"t":0,"s":[0]},{"i":{"x":[0.833],"y":[0.833]},"o":{"x":[0.167],"y":[0.167]},"t":104,"s":[100]},{"i":{"x":[0.833],"y":[0.833]},"o":{"x":[0.167],"y":[0.167]},"t":201,"s":[100]},{"i":{"x":[0.833],"y":[0.833]},"o":{"x":[0.167],"y":[0.167]},"t":252,"s":[0]},{"t":311,"s":[100]}],"ix":2},"o":{"a":0,"k":-23,"ix":3},"m":1,"ix":2,"nm":"Réduire les tracés 1","mn":"ADBE Vector Filter - Trim","hd":false}],"ip":0,"op":1257,"st":0,"bm":0},{"ddd":0,"ind":2,"ty":4,"nm":"Calque de forme 3","sr":1,"ks":{"o":{"a":0,"k":100,"ix":11},"r":{"a":0,"k":0,"ix":10},"p":{"a":0,"k":[756,491,0],"ix":2,"l":2},"a":{"a":0,"k":[0,0,0],"ix":1,"l":2},"s":{"a":0,"k":[59,59,100],"ix":6,"l":2}},"ao":0,"ef":[{"ty":5,"nm":"CC Light Sweep","np":11,"mn":"CC Light Sweep","ix":1,"en":1,"ef":[{"ty":3,"nm":"Center","mn":"CC Light Sweep-0001","ix":1,"v":{"a":1,"k":[{"i":{"x":0.833,"y":0.833},"o":{"x":0.167,"y":0.167},"t":0,"s":[76,245.5],"to":[0,0],"ti":[0,0]},{"t":311,"s":[1464,245.5]}],"ix":1}},{"ty":0,"nm":"Direction","mn":"CC Light Sweep-0002","ix":2,"v":{"a":0,"k":-30,"ix":2}},{"ty":7,"nm":"Shape","mn":"CC Light Sweep-0003","ix":3,"v":{"a":0,"k":1,"ix":3}},{"ty":0,"nm":"Width","mn":"CC Light Sweep-0004","ix":4,"v":{"a":0,"k":341,"ix":4}},{"ty":0,"nm":"Sweep Intensity","mn":"CC Light Sweep-0005","ix":5,"v":{"a":0,"k":40,"ix":5}},{"ty":0,"nm":"Edge Intensity","mn":"CC Light Sweep-0006","ix":6,"v":{"a":0,"k":74,"ix":6}},{"ty":0,"nm":"Edge Thickness","mn":"CC Light Sweep-0007","ix":7,"v":{"a":0,"k":0,"ix":7}},{"ty":2,"nm":"Light Color","mn":"CC Light Sweep-0008","ix":8,"v":{"a":0,"k":[1,1,1,1],"ix":8}},{"ty":7,"nm":"Light Reception","mn":"CC Light Sweep-0009","ix":9,"v":{"a":0,"k":1,"ix":9}}]}],"shapes":[{"ty":"gr","it":[{"ind":0,"ty":"sh","ix":1,"ks":{"a":0,"k":{"i":[[0,0],[0,0],[0,0],[0,0],[0,0],[0,0],[0,0],[0,0],[0,0]],"o":[[0,0],[0,0],[0,0],[0,0],[0,0],[0,0],[0,0],[0,0],[0,0]],"v":[[95.36,98.22],[217.02,218.75],[238.7,241.57],[238.73,241.6],[238.76,241.63],[398.14,401.01],[289.05,401.01],[-16.81,98.24],[95.37,98.24]],"c":false},"ix":2},"nm":"Tracé 1","mn":"ADBE Vector Shape - Group","hd":false},{"ty":"tm","s":{"a":0,"k":0,"ix":1},"e":{"a":1,"k":[{"i":{"x":[0.833],"y":[0.833]},"o":{"x":[0.167],"y":[0.167]},"t":94,"s":[0]},{"i":{"x":[0.833],"y":[0.833]},"o":{"x":[0.167],"y":[0.167]},"t":132,"s":[100]},{"i":{"x":[0.833],"y":[0.833]},"o":{"x":[0.167],"y":[0.167]},"t":150,"s":[100]},{"i":{"x":[0.833],"y":[0.833]},"o":{"x":[0.167],"y":[0.167]},"t":201,"s":[0]},{"i":{"x":[0.833],"y":[0.833]},"o":{"x":[0.167],"y":[0.167]},"t":296,"s":[0]},{"t":301,"s":[100]}],"ix":2},"o":{"a":0,"k":0,"ix":3},"m":1,"ix":2,"nm":"Réduire les tracés 1","mn":"ADBE Vector Filter - Trim","hd":false},{"ty":"st","c":{"a":0,"k":[1,1,1,1],"ix":3},"o":{"a":1,"k":[{"i":{"x":[0.833],"y":[0.833]},"o":{"x":[0.167],"y":[0.167]},"t":111,"s":[100]},{"i":{"x":[0.833],"y":[0.833]},"o":{"x":[0.167],"y":[0.167]},"t":112,"s":[100]},{"i":{"x":[0.833],"y":[0.833]},"o":{"x":[0.167],"y":[0.167]},"t":202,"s":[0]},{"t":355,"s":[0]}],"ix":4},"w":{"a":1,"k":[{"i":{"x":[0.833],"y":[0.833]},"o":{"x":[0.167],"y":[0.167]},"t":0,"s":[4]},{"i":{"x":[0.833],"y":[0.833]},"o":{"x":[0.167],"y":[0.167]},"t":64,"s":[4]},{"i":{"x":[0.833],"y":[0.833]},"o":{"x":[0.167],"y":[0.167]},"t":301,"s":[4]},{"t":311,"s":[0]}],"ix":5},"lc":1,"lj":1,"ml":4,"bm":0,"nm":"Contour 1","mn":"ADBE Vector Graphic - Stroke","hd":false},{"ty":"fl","c":{"a":1,"k":[{"i":{"x":[0.833],"y":[0.833]},"o":{"x":[0.167],"y":[0.167]},"t":552,"s":[1,1,1,1]},{"t":553,"s":[0,0,0,1]}],"ix":4},"o":{"a":1,"k":[{"i":{"x":[0.833],"y":[0.833]},"o":{"x":[0.167],"y":[0.167]},"t":279,"s":[0]},{"i":{"x":[0.833],"y":[0.833]},"o":{"x":[0.167],"y":[0.167]},"t":309,"s":[0]},{"i":{"x":[0.833],"y":[0.833]},"o":{"x":[0.167],"y":[0.167]},"t":310,"s":[100]},{"i":{"x":[0.833],"y":[0.833]},"o":{"x":[0.167],"y":[0.167]},"t":367,"s":[100]},{"t":372,"s":[7]}],"ix":5},"r":1,"bm":0,"nm":"Fond 1","mn":"ADBE Vector Graphic - Fill","hd":false},{"ty":"tr","p":{"a":0,"k":[0,0],"ix":2},"a":{"a":0,"k":[0,0],"ix":1},"s":{"a":1,"k":[{"i":{"x":[0.833,0.833],"y":[1,1]},"o":{"x":[0.511,0.511],"y":[-0.038,-0.038]},"t":359,"s":[100,100]},{"i":{"x":[0.703,0.703],"y":[0.732,0.732]},"o":{"x":[0.507,0.507],"y":[0.003,0.003]},"t":367,"s":[80,80]},{"t":377,"s":[400,400]}],"ix":3},"r":{"a":0,"k":0,"ix":6},"o":{"a":1,"k":[{"i":{"x":[0.833],"y":[0.833]},"o":{"x":[0.167],"y":[0.167]},"t":367,"s":[100]},{"t":377,"s":[0]}],"ix":7},"sk":{"a":0,"k":0,"ix":4},"sa":{"a":0,"k":0,"ix":5},"nm":"Transformar"}],"nm":"Forme 1","np":4,"cix":2,"bm":0,"ix":1,"mn":"ADBE Vector Group","hd":false}],"ip":55,"op":1225,"st":0,"bm":0}]}],"layers":[{"ddd":0,"ind":1,"ty":0,"nm":"quantum","refId":"comp_0","sr":1,"ks":{"o":{"a":0,"k":100,"ix":11},"r":{"a":0,"k":0,"ix":10},"p":{"a":0,"k":[1512,982,0],"ix":2,"l":2},"a":{"a":0,"k":[756,491,0],"ix":1,"l":2},"s":{"a":0,"k":[200,200,100],"ix":6,"l":2}},"ao":0,"w":1512,"h":982,"ip":0,"op":1215,"st":0,"bm":0},{"ddd":0,"ind":2,"ty":0,"nm":"Q","refId":"comp_1","sr":1,"ks":{"o":{"a":0,"k":100,"ix":11},"r":{"a":0,"k":0,"ix":10},"p":{"a":0,"k":[1512,982,0],"ix":2,"l":2},"a":{"a":0,"k":[756,491,0],"ix":1,"l":2},"s":{"a":0,"k":[200,200,100],"ix":6,"l":2}},"ao":0,"w":1512,"h":982,"ip":0,"op":1215,"st":0,"bm":0},{"ddd":0,"ind":3,"ty":1,"nm":"Branco Sólido 2","sr":1,"ks":{"o":{"a":0,"k":100,"ix":11},"r":{"a":0,"k":0,"ix":10},"p":{"a":0,"k":[1512,982,0],"ix":2,"l":2},"a":{"a":0,"k":[756,491,0],"ix":1,"l":2},"s":{"a":0,"k":[200,200,100],"ix":6,"l":2}},"ao":0,"sw":1512,"sh":982,"sc":"#f2f2f2","ip":377,"op":1225,"st":10,"bm":0}],"markers":[]}